odoo/addons/mrp_production_date_planned_finished_calendar/README.rst
odoo/addons/mrp_production_date_planned_finished_calendar/__init__.py
odoo/addons/mrp_production_date_planned_finished_calendar/__manifest__.py
odoo/addons/mrp_production_date_planned_finished_calendar/i18n/mrp_production_date_planned_finished_calendar.pot
odoo/addons/mrp_production_date_planned_finished_calendar/models/__init__.py
odoo/addons/mrp_production_date_planned_finished_calendar/models/mrp_production.py
odoo/addons/mrp_production_date_planned_finished_calendar/readme/CONTRIBUTORS.rst
odoo/addons/mrp_production_date_planned_finished_calendar/readme/DESCRIPTION.rst
odoo/addons/mrp_production_date_planned_finished_calendar/static/description/icon.png
odoo/addons/mrp_production_date_planned_finished_calendar/static/description/index.html
odoo/addons/mrp_production_date_planned_finished_calendar/tests/__init__.py
odoo/addons/mrp_production_date_planned_finished_calendar/tests/test_date_planned_finished_calendar.py
odoo_addon_mrp_production_date_planned_finished_calendar-15.0.1.0.1.dist-info/METADATA
odoo_addon_mrp_production_date_planned_finished_calendar-15.0.1.0.1.dist-info/WHEEL
odoo_addon_mrp_production_date_planned_finished_calendar-15.0.1.0.1.dist-info/top_level.txt
odoo_addon_mrp_production_date_planned_finished_calendar-15.0.1.0.1.dist-info/RECORD
