Metadata-Version: 2.1
Name: odoo-addon-mrp_production_date_planned_finished_calendar
Version: 15.0.1.0.1
Summary: Allows to plan production from the desired finish date
Home-page: https://github.com/OCA/manufacture
Author: ForgeFlow, Odoo Community Association (OCA)
Author-email: support@odoo-community.org
License: AGPL-3
Classifier: Programming Language :: Python
Classifier: Framework :: Odoo
Classifier: Framework :: Odoo :: 15.0
Classifier: License :: OSI Approved :: GNU Affero General Public License v3
Requires-Python: >=3.8
Requires-Dist: odoo-addon-mrp-production-date-planned-finished<15.1dev,>=15.0dev
Requires-Dist: odoo-addon-mrp-warehouse-calendar<15.1dev,>=15.0dev
Requires-Dist: odoo<15.1dev,>=15.0a
